nucos/__init__.py
nucos/lat_long.py
nucos/unit_conversion.py
nucos/unit_data.py
nucos/tests/__init__.py
nucos/tests/test_dump.py
nucos/tests/test_lat_long.py
nucos/tests/test_old_api.py
nucos/tests/test_unit_conversion.py
unit_conversion/__init__.py
pynucos-3.4.0.dist-info/LICENSE
pynucos-3.4.0.dist-info/METADATA
pynucos-3.4.0.dist-info/WHEEL
pynucos-3.4.0.dist-info/top_level.txt
pynucos-3.4.0.dist-info/RECORD
