Metadata-Version: 2.2
Name: pynucos
Version: 3.4.0
Summary: Physical Unit conversion utilities -- units useful for oil and chemical spill response
Home-page: https://github.com/NOAA-ORR-ERD/PyNUCOS
Author: Christopher H. Barker
Author-email: Chris.Barker@noaa.gov
Project-URL: Bug Tracker, https://github.com/NOAA-ORR-ERD/PyNUCOS/issues
Classifier: Programming Language :: Python :: 3
Classifier: Operating System :: OS Independent
Classifier: Development Status :: 5 - Production/Stable
Classifier: Intended Audience :: Developers
Classifier: Intended Audience :: Science/Research
Classifier: License :: CC0 1.0 Universal (CC0 1.0) Public Domain Dedication
Classifier: Programming Language :: Python :: 3 :: Only
Classifier: Topic :: Scientific/Engineering
Requires-Python: >=3.9
License-File: LICENSE
